django_react_templatetags_es_modules
