Metadata-Version: 2.1
Name: django-react-templatetags-es-modules
Version: 1.0.2
Summary: This django library allows you to add React components into your django templates.
Home-page: https://github.com/AriaMoradi/django-react-templatetags-es-modlues
Author: Aria Moradi
Author-email: aria.moradi007@gmail.com
License: MIT
Platform: UNKNOWN
Classifier: Development Status :: 5 - Production/Stable
Classifier: Environment :: Web Environment
Classifier: Intended Audience :: Developers
Classifier: Natural Language :: English
Classifier: Intended Audience :: Developers
Classifier: License :: OSI Approved :: MIT License
Classifier: Programming Language :: Python
Classifier: Programming Language :: Python :: 2
Classifier: Programming Language :: Python :: 2.7
Classifier: Programming Language :: Python :: 3
Classifier: Programming Language :: Python :: 3.5
Classifier: Programming Language :: Python :: 3.6
Classifier: Programming Language :: Python :: 3.7
Classifier: Framework :: Django
Classifier: Topic :: Utilities
Classifier: Programming Language :: JavaScript
Provides-Extra: ssr
